mocket/__init__.py
mocket/compat.py
mocket/entry.py
mocket/exceptions.py
mocket/inject.py
mocket/io.py
mocket/mocket.py
mocket/mode.py
mocket/recording.py
mocket/socket.py
mocket/types.py
mocket/urllib3.py
mocket/utils.py
mocket/decorators/__init__.py
mocket/decorators/async_mocket.py
mocket/decorators/mocketizer.py
mocket/mocks/__init__.py
mocket/mocks/mockhttp.py
mocket/mocks/mockredis.py
mocket/plugins/__init__.py
mocket/plugins/aiohttp_connector.py
mocket/plugins/pook_mock_engine.py
mocket/plugins/httpretty/__init__.py
mocket/ssl/__init__.py
mocket/ssl/context.py
mocket/ssl/socket.py
mocket-3.14.0.dist-info/METADATA
mocket-3.14.0.dist-info/WHEEL
mocket-3.14.0.dist-info/licenses/LICENSE
mocket-3.14.0.dist-info/RECORD
