Metadata-Version: 2.4
Name: mocket
Version: 3.14.0
Summary: Socket Mock Framework - for all kinds of socket animals, web-clients included - with gevent/asyncio/SSL support
Project-URL: Homepage, https://pypi.org/project/mocket
Project-URL: Repository, https://github.com/mindflayer/python-mocket
Author-email: Giorgio Salluzzo <giorgio.salluzzo@gmail.com>
License: Copyright (c) 2017-2025 Giorgio Salluzzo and individual contributors. All rights reserved.
License-File: LICENSE
Classifier: Development Status :: 6 - Mature
Classifier: Intended Audience :: Developers
Classifier: License :: OSI Approved :: BSD License
Classifier: Operating System :: OS Independent
Classifier: Programming Language :: Python :: 3.8
Classifier: Programming Language :: Python :: 3.9
Classifier: Programming Language :: Python :: 3.10
Classifier: Programming Language :: Python :: 3.11
Classifier: Programming Language :: Python :: 3.12
Classifier: Programming Language :: Python :: 3.13
Classifier: Programming Language :: Python :: 3.14
Classifier: Programming Language :: Python :: Implementation :: CPython
Classifier: Programming Language :: Python :: Implementation :: PyPy
Classifier: Topic :: Software Development
Classifier: Topic :: Software Development :: Testing
Requires-Python: >=3.8
Requires-Dist: decorator>=4.0.0
Requires-Dist: h11
Requires-Dist: puremagic
Requires-Dist: typing-extensions
Requires-Dist: urllib3>=1.25.3
Provides-Extra: pook
Requires-Dist: pook>=0.2.1; extra == 'pook'
Provides-Extra: speedups
Requires-Dist: xxhash-cffi; (platform_python_implementation == 'PyPy') and extra == 'speedups'
Requires-Dist: xxhash; (platform_python_implementation == 'CPython') and extra == 'speedups'
Provides-Extra: test
Requires-Dist: aiohttp; extra == 'test'
Requires-Dist: asgiref; extra == 'test'
Requires-Dist: build; extra == 'test'
Requires-Dist: fastapi; extra == 'test'
Requires-Dist: flake8>5; extra == 'test'
Requires-Dist: gevent; extra == 'test'
Requires-Dist: httpx; extra == 'test'
Requires-Dist: mypy; extra == 'test'
Requires-Dist: pipfile; extra == 'test'
Requires-Dist: pre-commit; extra == 'test'
Requires-Dist: psutil; extra == 'test'
Requires-Dist: pytest; extra == 'test'
Requires-Dist: pytest-asyncio; extra == 'test'
Requires-Dist: pytest-cov; extra == 'test'
Requires-Dist: redis; extra == 'test'
Requires-Dist: requests; extra == 'test'
Requires-Dist: sure; extra == 'test'
Requires-Dist: trio; extra == 'test'
Requires-Dist: types-decorator; extra == 'test'
Requires-Dist: types-requests; extra == 'test'
Requires-Dist: wait-for-it; extra == 'test'
Requires-Dist: xxhash; extra == 'test'
